ectool/__init__.py
ectool/ecaction.py
ectool/ecag.py
ectool/eccli.py
ectool/ecconst.py
ectool/eclogs.py
ectool/ecstruct.py
ectool/unpkg.py
ectool-1.2.1.dist-info/LICENSE
ectool-1.2.1.dist-info/METADATA
ectool-1.2.1.dist-info/WHEEL
ectool-1.2.1.dist-info/entry_points.txt
ectool-1.2.1.dist-info/top_level.txt
ectool-1.2.1.dist-info/RECORD
