Metadata-Version: 2.1
Name: ectool
Version: 1.2.1
Summary: A tools for EC modules, like EC618/EC616/EC718
Home-page: https://github.com/openLuat/ectool2py
Author: Wendal Chen
Project-URL: Bug Reports, https://github.com/openLuat/ectool2py/issues
Project-URL: Source, https://github.com/openLuat/ectool2py/
Keywords: ec618,development
Classifier: Development Status :: 4 - Beta
Classifier: Intended Audience :: Developers
Classifier: Topic :: Software Development :: Build Tools
Classifier: License :: OSI Approved :: MIT License
Classifier: Programming Language :: Python :: 3
Classifier: Programming Language :: Python :: 3.7
Classifier: Programming Language :: Python :: 3.8
Classifier: Programming Language :: Python :: 3.9
Classifier: Programming Language :: Python :: 3.10
Classifier: Programming Language :: Python :: 3.11
Classifier: Programming Language :: Python :: 3 :: Only
Requires-Python: >=3.7, <4
License-File: LICENSE
Requires-Dist: cstruct
Requires-Dist: pyserial
Requires-Dist: py7zr
Provides-Extra: dev
Requires-Dist: check-manifest ; extra == 'dev'
Provides-Extra: test
Requires-Dist: coverage ; extra == 'test'
